Ecmascript51GuifanZhongwenban/README.md
Ecmascript51GuifanZhongwenban/__init__.py
Ecmascript51GuifanZhongwenban/__main__.py
Ecmascript51GuifanZhongwenban/file.epub
Ecmascript51GuifanZhongwenban/index.html
Ecmascript51GuifanZhongwenban/css/__init__.py
Ecmascript51GuifanZhongwenban/css/annotations.css
Ecmascript51GuifanZhongwenban/css/main.css
Ecmascript51GuifanZhongwenban/css/normalize.css
Ecmascript51GuifanZhongwenban/css/popup.css
Ecmascript51GuifanZhongwenban/font/__init__.py
Ecmascript51GuifanZhongwenban/font/fontello.eot
Ecmascript51GuifanZhongwenban/font/fontello.svg
Ecmascript51GuifanZhongwenban/font/fontello.ttf
Ecmascript51GuifanZhongwenban/font/fontello.woff
Ecmascript51GuifanZhongwenban/img/__init__.py
Ecmascript51GuifanZhongwenban/img/annotator-glyph-sprite.png
Ecmascript51GuifanZhongwenban/img/annotator-icon-sprite.png
Ecmascript51GuifanZhongwenban/img/apple-touch-icon.png
Ecmascript51GuifanZhongwenban/img/cancelfullscreen.png
Ecmascript51GuifanZhongwenban/img/close.png
Ecmascript51GuifanZhongwenban/img/fullscreen.png
Ecmascript51GuifanZhongwenban/img/loader.gif
Ecmascript51GuifanZhongwenban/img/menu-icon.png
Ecmascript51GuifanZhongwenban/img/save.png
Ecmascript51GuifanZhongwenban/img/saved.png
Ecmascript51GuifanZhongwenban/img/settings-s.png
Ecmascript51GuifanZhongwenban/img/settings.png
Ecmascript51GuifanZhongwenban/img/star.png
Ecmascript51GuifanZhongwenban/js/__init__.py
Ecmascript51GuifanZhongwenban/js/epub.js
Ecmascript51GuifanZhongwenban/js/epub.min.js
Ecmascript51GuifanZhongwenban/js/epub.min.map
Ecmascript51GuifanZhongwenban/js/hooks.min.js
Ecmascript51GuifanZhongwenban/js/hooks.min.map
Ecmascript51GuifanZhongwenban/js/reader.js
Ecmascript51GuifanZhongwenban/js/reader.js.map
Ecmascript51GuifanZhongwenban/js/reader.min.js
Ecmascript51GuifanZhongwenban/js/reader.min.map
Ecmascript51GuifanZhongwenban/js/hooks/__init__.py
Ecmascript51GuifanZhongwenban/js/hooks/extensions/__init__.py
Ecmascript51GuifanZhongwenban/js/hooks/extensions/highlight.js
ecmascript_5_1_guifan_zhongwenban-2024.3.1.0.dist-info/METADATA
ecmascript_5_1_guifan_zhongwenban-2024.3.1.0.dist-info/WHEEL
ecmascript_5_1_guifan_zhongwenban-2024.3.1.0.dist-info/entry_points.txt
ecmascript_5_1_guifan_zhongwenban-2024.3.1.0.dist-info/top_level.txt
ecmascript_5_1_guifan_zhongwenban-2024.3.1.0.dist-info/RECORD
